README.md
setup.cfg
setup.py
accubits/__init__.py
accubits/main.py
accubits/utils.py
accubits.egg-info/PKG-INFO
accubits.egg-info/SOURCES.txt
accubits.egg-info/dependency_links.txt
accubits.egg-info/entry_points.txt
accubits.egg-info/requires.txt
accubits.egg-info/top_level.txt