Metadata-Version: 2.1
Name: accubits
Version: 0.5
Summary: CLI Tool to create front end web apps from boilerplate code
Home-page: UNKNOWN
Author: Nithi
Author-email: bearnithi@gmail.com
License: MIT
Download-URL: https://github.com/accubits-tech/accubits-cli/archive/0.5.tar.gz
Keywords: Accubits Cli,Front end boilerplates,angular boilerplate
Platform: UNKNOWN
